mkproj/__init__.py
mkproj/templates/bash/{{ project_name }}.sh
mkproj/templates/cpp/{{ project_name }}/.gitignore
mkproj/templates/cpp/{{ project_name }}/Makefile
mkproj/templates/cpp/{{ project_name }}/Readme.md
mkproj/templates/cpp/{{ project_name }}/include/{{ project_name }}.h
mkproj/templates/cpp/{{ project_name }}/src/main.cpp
mkproj/templates/python/{{ project_name }}/MANIFEST.in
mkproj/templates/python/{{ project_name }}/README.md
mkproj/templates/python/{{ project_name }}/setup.py
mkproj/templates/python/{{ project_name }}/{{ project_name }}/__init__.py
mkproj/templates/python/{{ project_name }}/{{ project_name }}/data/{{ project_name}}.txt
mkproj-0.2.dist-info/LICENSE
mkproj-0.2.dist-info/METADATA
mkproj-0.2.dist-info/WHEEL
mkproj-0.2.dist-info/entry_points.txt
mkproj-0.2.dist-info/top_level.txt
mkproj-0.2.dist-info/RECORD
