Metadata-Version: 2.1
Name: mkproj
Version: 0.2
Summary: A tool to generate scaffolding for C++ and Python projects
License-File: LICENSE
Requires-Dist: jinja2
Requires-Dist: argparse
